toggl2moneybird/__init__.py
toggl2moneybird/__main__.py
toggl2moneybird/cli.py
toggl2moneybird/commands.py
toggl2moneybird/menu.py
toggl2moneybird/moneybird.py
toggl2moneybird/sync.py
toggl2moneybird/toggl.py
toggl2moneybird-0.5.2.dist-info/LICENSE
toggl2moneybird-0.5.2.dist-info/METADATA
toggl2moneybird-0.5.2.dist-info/WHEEL
toggl2moneybird-0.5.2.dist-info/entry_points.txt
toggl2moneybird-0.5.2.dist-info/top_level.txt
toggl2moneybird-0.5.2.dist-info/RECORD
