Metadata-Version: 2.1
Name: toggl2moneybird
Version: 0.5.2
Summary: User-friendly command-line tool for synchronizing time entries from Toggl Track to Moneybird
Author-email: rdb <me@rdb.name>
License: MIT License
Project-URL: Source, https://github.com/rdb/toggl2moneybird
Project-URL: Bug Tracker, https://github.com/rdb/toggl2moneybird/issues
Classifier: Programming Language :: Python :: 3
Classifier: License :: OSI Approved :: MIT License
Classifier: Topic :: Office/Business :: Financial :: Accounting
Requires-Python: >=3.8
License-File: LICENSE
Requires-Dist: keyring
Requires-Dist: requests
Requires-Dist: rich
Requires-Dist: rich-argparse
